twypy-1.0.0.dist-info/METADATA
twypy-1.0.0.dist-info/WHEEL
twypy-1.0.0.dist-info/DESCRIPTION.rst
twypy-1.0.0.dist-info/RECORD
twypy-1.0.0.dist-info/top_level.txt
twypy-1.0.0.dist-info/metadata.json
twypy/__init__.py
twypy/api.py
