Metadata-Version: 2.0
Name: twypy
Version: 1.0.0
Summary: Twitter REST API v1.1 client for Python
Home-page: https://github.com/rogerfernandezg/twypy/
Author: Roger Fernandez Guri
Author-email: rogerfernandezguri@me.com
License: The MIT License (MIT)
Requires-Dist: requests-oauthlib (>=0.3.2)
